dockerfile_parse-stubs/METADATA.toml
dockerfile_parse-stubs/__init__.pyi
dockerfile_parse-stubs/constants.pyi
dockerfile_parse-stubs/parser.pyi
dockerfile_parse-stubs/py.typed
dockerfile_parse-stubs/util.pyi
types_dockerfile_parse-2.0.0.20250708.dist-info/licenses/LICENSE
types_dockerfile_parse-2.0.0.20250708.dist-info/METADATA
types_dockerfile_parse-2.0.0.20250708.dist-info/WHEEL
types_dockerfile_parse-2.0.0.20250708.dist-info/top_level.txt
types_dockerfile_parse-2.0.0.20250708.dist-info/RECORD
